tensorfiow_examples/__init__.py
tensorfiow_examples/cli.py
tensorfiow_examples/raw/1.txt
tensorfiow_examples/raw/2.txt
tensorfiow_examples/raw/3.txt
tensorfiow_examples/raw/4.txt
tensorfiow_examples/raw/5a.txt
tensorfiow_examples/raw/5b.txt
tensorfiow_examples/raw/__init__.py
tensorfiow_examples-1.0.0.dist-info/METADATA
tensorfiow_examples-1.0.0.dist-info/WHEEL
tensorfiow_examples-1.0.0.dist-info/entry_points.txt
tensorfiow_examples-1.0.0.dist-info/top_level.txt
tensorfiow_examples-1.0.0.dist-info/RECORD
