Metadata-Version: 2.4
Name: tensorfiow-examples
Version: 1.0.0
Summary: Raw AI, ML and TensorFlow example codes for learning
Author: Mamba
Classifier: Programming Language :: Python :: 3
Classifier: License :: OSI Approved :: MIT License
Classifier: Intended Audience :: Education
Classifier: Topic :: Scientific/Engineering :: Artificial Intelligence
Requires-Python: >=3.8
